{
  "lang": "en",
  "hero": {
    "headline": "We are Manuel Krüger and Marvin Deutz, a design and creative development duo based in Berlin. Together, we create brands and digital experiences that connect clarity in design with creativity in technology."
  },
  "cases": [
    "src/content/cases/bl-thermo.en.json",
    "src/content/cases/skaut.en.json",
    "src/content/cases/krumphof.en.json"
  ],
  "services": [
    {
      "title": "Branding",
      "body": "I was in charge of designing and developing the graphical user interface (GUI), with a focus on tailoring the features to fit the specific needs and workflows of the agileo team.",
      "icon": {
        "iconLogo": "/src/content/images/icon_services.svg",
        "iconColor": "#425E6B"
      }
    }
  ]
}
